{
  "id": "contextPrimingFeedback",
  "title": "Contextual Priming and Feedback for Faster R-CNN",
  "authors": [
    "abhinav-shrivastava",
    "abhinav-gupta"
  ],
  "venue": "ECCV",
  "year": 2016,
  "tags": [],
  "links": {
    "pdf": "https://link.springer.com/content/pdf/10.1007/978-3-319-46448-0_20.pdf",
    "poster": "https://www.dropbox.com/scl/fi/pe7tznwbcx7f798r8oyvv/context_priming_feedback.pdf?rlkey=7t3oyzghs6h646ak6r2msal6d&dl=1"
  },
  "thumbnail": "images/primingfeedback3_compressed.png",
  "date": "2016-07"
}
